chuk_mcp_echo_server/__init__.py
chuk_mcp_echo_server/main.py
chuk_mcp_echo_server/models.py
chuk_mcp_echo_server/tools.py
chuk_mcp_echo_server-0.1.10.dist-info/licenses/LICENSE.md
chuk_mcp_echo_server-0.1.10.dist-info/METADATA
chuk_mcp_echo_server-0.1.10.dist-info/WHEEL
chuk_mcp_echo_server-0.1.10.dist-info/entry_points.txt
chuk_mcp_echo_server-0.1.10.dist-info/top_level.txt
chuk_mcp_echo_server-0.1.10.dist-info/RECORD
