Metadata-Version: 2.4
Name: chuk-mcp-echo-server
Version: 0.1.10
Summary: MCP Echo Server
Project-URL: Homepage, https://github.com/chrishayuk/chuk-mcp-servers
Project-URL: Bug Tracker, https://github.com/chrishayuk/chuk-mcp-servers/issues
Requires-Python: >=3.11
License-File: LICENSE.md
Requires-Dist: chuk-mcp-runtime>=0.1.7
Requires-Dist: mcp>=1.6.0
Requires-Dist: pydantic>=2.11.2
Requires-Dist: pyyaml>=6.0.2
Dynamic: license-file
